Metadata-Version: 2.4
Name: Radicale
Version: 3.6.0
Summary: CalDAV and CardDAV Server
Author-email: Guillaume Ayoub <guillaume.ayoub@kozea.fr>, Unrud <unrud@outlook.com>, Peter Bieringer <pb@bieringer.de>
License: GNU GPL v3
Project-URL: Homepage, https://radicale.org/
Keywords: calendar,addressbook,CalDAV,CardDAV
Platform: Any
Classifier: Development Status :: 5 - Production/Stable
Classifier: Environment :: Console
Classifier: Environment :: Web Environment
Classifier: Intended Audience :: End Users/Desktop
Classifier: Intended Audience :: Information Technology
Classifier: License :: OSI Approved :: GNU General Public License (GPL)
Classifier: Operating System :: OS Independent
Classifier: Programming Language :: Python :: 3
Classifier: Programming Language :: Python :: 3.9
Classifier: Programming Language :: Python :: 3.10
Classifier: Programming Language :: Python :: 3.11
Classifier: Programming Language :: Python :: 3.12
Classifier: Programming Language :: Python :: 3.13
Classifier: Programming Language :: Python :: Implementation :: CPython
Classifier: Programming Language :: Python :: Implementation :: PyPy
Classifier: Topic :: Office/Business :: Groupware
Requires-Python: >=3.9.0
License-File: COPYING.md
Requires-Dist: defusedxml
Requires-Dist: libpass>=1.9.3
Requires-Dist: vobject>=0.9.6
Requires-Dist: pika>=1.1.0
Requires-Dist: requests
Requires-Dist: packaging
Provides-Extra: test
Requires-Dist: pytest>=7; extra == "test"
Requires-Dist: waitress; extra == "test"
Requires-Dist: bcrypt; extra == "test"
Requires-Dist: argon2-cffi; extra == "test"
Provides-Extra: bcrypt
Requires-Dist: bcrypt; extra == "bcrypt"
Provides-Extra: argon2
Requires-Dist: argon2-cffi; extra == "argon2"
Provides-Extra: ldap
Requires-Dist: ldap3; extra == "ldap"
Dynamic: license-file
